wild_relation_network/__init__.py
wild_relation_network/layers.py
wild_relation_network/relation_network.py
wild_relation_network/wild_relation_network.py
wild_relation_network-0.1.0.dist-info/LICENSE
wild_relation_network-0.1.0.dist-info/METADATA
wild_relation_network-0.1.0.dist-info/WHEEL
wild_relation_network-0.1.0.dist-info/top_level.txt
wild_relation_network-0.1.0.dist-info/RECORD
