Metadata-Version: 2.1
Name: wild-relation-network
Version: 0.1.0
Summary: Wild Relation Network for solving Raven's Progressive Matrices
Home-page: https://github.com/mikomel/wild-relation-network
Author: Mikołaj Małkiński
Author-email: mikolaj.malkinski@gmail.com
License: MIT
Keywords: artificial intelligence,relation network,wild relation network
Platform: UNKNOWN
Classifier: Development Status :: 4 - Beta
Classifier: Intended Audience :: Developers
Classifier: License :: OSI Approved :: MIT License
Classifier: Operating System :: OS Independent
Classifier: Programming Language :: Python :: 3.6
Classifier: Topic :: Scientific/Engineering :: Artificial Intelligence
Requires-Python: >=3.6
Requires-Dist: torch (>=1.5)
